aion/__init__.py
aion/cli.py
aion/code.py
aion/embed.py
aion/evaluate.py
aion/files.py
aion/parser.py
aion/prompt.py
aion/snippets.py
aion/text.py
aion/utils.py
aion/watcher.py
linkai_aion-0.1.6.dist-info/METADATA
linkai_aion-0.1.6.dist-info/WHEEL
linkai_aion-0.1.6.dist-info/top_level.txt
linkai_aion-0.1.6.dist-info/RECORD
