Metadata-Version: 2.4
Name: linkai-aion
Version: 0.1.6
Summary: 🚀 LinkAI-Aion v0.1.6 — Enhanced AI Utilities with File Management, Code Parsing, and Real-time Monitoring
Home-page: https://linkaiapps.com/#linkai-aion
Author: Aksel
Author-email: Aksel <aksel@linkaiapps.com>
Project-URL: Homepage, https://linkaiapps.com/#linkai-aion
Project-URL: PyPI, https://pypi.org/project/linkai-aion/
Keywords: utilities,text-processing,file-handling,cli,developer-tools,linkai
Classifier: Development Status :: 4 - Beta
Classifier: Intended Audience :: Developers
Classifier: Operating System :: OS Independent
Classifier: Programming Language :: Python :: 3
Classifier: Programming Language :: Python :: 3.8
Classifier: Programming Language :: Python :: 3.9
Classifier: Programming Language :: Python :: 3.10
Classifier: Programming Language :: Python :: 3.11
Classifier: Programming Language :: Python :: 3.12
Classifier: Topic :: Software Development :: Libraries :: Python Modules
Classifier: Topic :: Text Processing
Classifier: Topic :: Utilities
Requires-Python: >=3.8
Provides-Extra: dev
Requires-Dist: pytest>=6.0; extra == "dev"
Requires-Dist: black>=21.0; extra == "dev"
Requires-Dist: flake8>=3.8; extra == "dev"
Dynamic: author
Dynamic: home-page
Dynamic: requires-python
